pseudo_labeller/__init__.py
pseudo_labeller/model/__init__.py
pseudo_labeller/model/idam.py
pseudo_labeller/utils/__init__.py
pseudo_labeller-0.0.14.dist-info/LICENSE
pseudo_labeller-0.0.14.dist-info/METADATA
pseudo_labeller-0.0.14.dist-info/WHEEL
pseudo_labeller-0.0.14.dist-info/top_level.txt
pseudo_labeller-0.0.14.dist-info/RECORD
