Metadata-Version: 2.1
Name: pseudo-labeller
Version: 0.0.14
Summary: Psuedo PV/Irradience Labeller
Author: Jacob Bieker
Author-email: info@openclimatefix.org
License: MIT
License-File: LICENSE
Requires-Dist: torch
Requires-Dist: einops
Requires-Dist: huggingface-hub
